arxiv2md/__init__.py
arxiv2md/_api.py
arxiv2md/_convert.py
arxiv2md/_utils.py
arxiv2md/cli.py
arxiv2md-0.1.0.dist-info/METADATA
arxiv2md-0.1.0.dist-info/WHEEL
arxiv2md-0.1.0.dist-info/entry_points.txt
arxiv2md-0.1.0.dist-info/licenses/LICENSE
arxiv2md-0.1.0.dist-info/RECORD
