Metadata-Version: 2.4
Name: arxiv2md
Version: 0.1.0
Summary: A command-line tool and Python library to convert arXiv papers to Markdown format.
Project-URL: Homepage, https://github.com/misya11p/arxiv2md
Author-email: komiya <90894519+misya11p@users.noreply.github.com>
License: MIT License Copyright (c) 2025 komiya
License-File: LICENSE
Keywords: arxiv,converter,markdown
Classifier: Development Status :: 4 - Beta
Classifier: Intended Audience :: Science/Research
Classifier: License :: OSI Approved :: MIT License
Classifier: Programming Language :: Python :: 3
Classifier: Programming Language :: Python :: 3.10
Classifier: Programming Language :: Python :: 3.11
Classifier: Programming Language :: Python :: 3.12
Requires-Python: >=3.10
Requires-Dist: arxiv>=2.2.0
Requires-Dist: bs4>=0.0.2
Requires-Dist: halo>=0.0.31
Requires-Dist: lxml>=6.0.0
Requires-Dist: requests>=2.32.5
Requires-Dist: typer>=0.16.1
